{
  "formatVersion": "1.0",
  "id": "YumboalCubo2025",
  "name": "Yumbo al Cubo 2025",
  "shortName": "Yumbo al Cubo 2025",
  "series": null,
  "persons": [
    {
      "name": "Paloma Sarmiento",
      "wcaUserId": 494328,
      "wcaId": null,
      "registrantId": 1,
      "countryIso2": "CO",
      "gender": "f",
      "registration": {
        "wcaRegistrationId": 1184903,
        "eventIds": [
          "333"
        ],
        "status": "accepted",
        "isCompeting": true
      },
      "avatar": null,
      "roles": [],
      "assignments": [],
      "personalBests": [],
      "extensions": []
    },
    {
      "name": "Damian Andres Posada Galarza",
      "wcaUserId": 480152,
      "wcaId": "2025GALA08",
      "registrantId": 2,
      "countryIso2": "CO",
      "gender": "m",
      "registration": {
        "wcaRegistrationId": 1184907,
        "eventIds": [
          "222",
          "333",
          "pyram",
          "skewb"
        ],
        "status": "accepted",
        "isCompeting": true
      },
      "avatar": null,
      "roles": [],
      "assignments": [],
      "personalBests": [
        {
          "eventId": "222",
          "best": 1377,
          "worldRanking": 126727,
          "continentalRanking": 10585,
          "nationalRanking": 2304,
          "type": "average"
        },
        {
          "eventId": "333",
          "best": 4069,
          "worldRanking": 173364,
          "continentalRanking": 15926,
          "nationalRanking": 3193,
          "type": "average"
        },
        {
          "eventId": "pyram",
          "best": 1311,
          "worldRanking": 52125,
          "continentalRanking": 3632,
          "nationalRanking": 826,
          "type": "average"
        },
        {
          "eventId": "222",
          "best": 1258,
          "worldRanking": 144837,
          "continentalRanking": 12447,
          "nationalRanking": 2694,
          "type": "single"
        },
        {
          "eventId": "333",
          "best": 3589,
          "worldRanking": 182763,
          "continentalRanking": 17005,
          "nationalRanking": 3438,
          "type": "single"
        },
        {
          "eventId": "pyram",
          "best": 1214,
          "worldRanking": 79260,
          "continentalRanking": 5917,
          "nationalRanking": 1338,
          "type": "single"
        }
      ],
      "extensions": []
    },
    {
      "name": "Ricardo Zapata Cruz",
      "wcaUserId": 76246,
      "wcaId": "2018CRUZ17",
      "registrantId": 3,
      "countryIso2": "VE",
      "gender": "m",
      "registration": {
        "wcaRegistrationId": 1184915,
        "eventIds": [
          "222",
          "333",
          "333oh",
          "444",
          "clock",
          "pyram",
          "skewb"
        ],
        "status": "accepted",
        "isCompeting": true
      },
      "avatar": {
        "url": "https://avatars.worldcubeassociation.org/uploads/user/avatar/2018CRUZ17/1659680377.JPG",
        "thumbUrl": "https://avatars.worldcubeassociation.org/uploads/user/avatar/2018CRUZ17/1659680377_thumb.JPG"
      },
      "roles": [],
      "assignments": [],
      "personalBests": [
        {
          "eventId": "222",
          "best": 287,
          "worldRanking": 3200,
          "continentalRanking": 191,
          "nationalRanking": 7,
          "type": "average"
        },
        {
          "eventId": "333",
          "best": 1021,
          "worldRanking": 7795,
          "continentalRanking": 479,
          "nationalRanking": 21,
          "type": "average"
        },
        {
          "eventId": "333bf",
          "best": 11233,
          "worldRanking": 1540,
          "continentalRanking": 92,
          "nationalRanking": 2,
          "type": "average"
        },
        {
          "eventId": "333oh",
          "best": 1563,
          "worldRanking": 2086,
          "continentalRanking": 134,
          "nationalRanking": 8,
          "type": "average"
        },
        {
          "eventId": "444",
          "best": 3676,
          "worldRanking": 2583,
          "continentalRanking": 167,
          "nationalRanking": 4,
          "type": "average"
        },
        {
          "eventId": "555",
          "best": 8089,
          "worldRanking": 4484,
          "continentalRanking": 276,
          "nationalRanking": 8,
          "type": "average"
        },
        {
          "eventId": "666",
          "best": 15123,
          "worldRanking": 2899,
          "continentalRanking": 176,
          "nationalRanking": 3,
          "type": "average"
        },
        {
          "eventId": "777",
          "best": 23676,
          "worldRanking": 2772,
          "continentalRanking": 169,
          "nationalRanking": 3,
          "type": "average"
        },
        {
          "eventId": "clock",
          "best": 1063,
          "worldRanking": 4936,
          "continentalRanking": 271,
          "nationalRanking": 7,
          "type": "average"
        },
        {
          "eventId": "minx",
          "best": 6652,
          "worldRanking": 2675,
          "continentalRanking": 261,
          "nationalRanking": 9,
          "type": "average"
        },
        {
          "eventId": "pyram",
          "best": 512,
          "worldRanking": 4374,
          "continentalRanking": 292,
          "nationalRanking": 10,
          "type": "average"
        },
        {
          "eventId": "skewb",
          "best": 440,
          "worldRanking": 1596,
          "continentalRanking": 87,
          "nationalRanking": 2,
          "type": "average"
        },
        {
          "eventId": "sq1",
          "best": 1313,
          "worldRanking": 1144,
          "continentalRanking": 69,
          "nationalRanking": 2,
          "type": "average"
        },
        {
          "eventId": "222",
          "best": 174,
          "worldRanking": 5099,
          "continentalRanking": 369,
          "nationalRanking": 13,
          "type": "single"
        },
        {
          "eventId": "333",
          "best": 826,
          "worldRanking": 7646,
          "continentalRanking": 486,
          "nationalRanking": 20,
          "type": "single"
        },
        {
          "eventId": "333bf",
          "best": 9842,
          "worldRanking": 2700,
          "continentalRanking": 152,
          "nationalRanking": 4,
          "type": "single"
        },
        {
          "eventId": "333fm",
          "best": 41,
          "worldRanking": 5644,
          "continentalRanking": 364,
          "nationalRanking": 16,
          "type": "single"
        },
        {
          "eventId": "333mbf",
          "best": 980051801,
          "worldRanking": 3061,
          "continentalRanking": 222,
          "nationalRanking": 4,
          "type": "single"
        },
        {
          "eventId": "333oh",
          "best": 1319,
          "worldRanking": 2914,
          "continentalRanking": 205,
          "nationalRanking": 9,
          "type": "single"
        },
        {
          "eventId": "444",
          "best": 3210,
          "worldRanking": 2813,
          "continentalRanking": 187,
          "nationalRanking": 7,
          "type": "single"
        },
        {
          "eventId": "444bf",
          "best": 69000,
          "worldRanking": 1231,
          "continentalRanking": 68,
          "nationalRanking": 2,
          "type": "single"
        },
        {
          "eventId": "555",
          "best": 6858,
          "worldRanking": 3437,
          "continentalRanking": 200,
          "nationalRanking": 5,
          "type": "single"
        },
        {
          "eventId": "666",
          "best": 14188,
          "worldRanking": 2979,
          "continentalRanking": 184,
          "nationalRanking": 3,
          "type": "single"
        },
        {
          "eventId": "777",
          "best": 22473,
          "worldRanking": 2849,
          "continentalRanking": 171,
          "nationalRanking": 2,
          "type": "single"
        },
        {
          "eventId": "clock",
          "best": 807,
          "worldRanking": 4027,
          "continentalRanking": 216,
          "nationalRanking": 6,
          "type": "single"
        },
        {
          "eventId": "minx",
          "best": 5932,
          "worldRanking": 2749,
          "continentalRanking": 266,
          "nationalRanking": 9,
          "type": "single"
        },
        {
          "eventId": "pyram",
          "best": 207,
          "worldRanking": 1345,
          "continentalRanking": 81,
          "nationalRanking": 4,
          "type": "single"
        },
        {
          "eventId": "skewb",
          "best": 217,
          "worldRanking": 1010,
          "continentalRanking": 69,
          "nationalRanking": 1,
          "type": "single"
        },
        {
          "eventId": "sq1",
          "best": 1050,
          "worldRanking": 1513,
          "continentalRanking": 85,
          "nationalRanking": 2,
          "type": "single"
        }
      ],
      "extensions": []
    },
    {
      "name": "Samuel German Giraldo Quintero",
      "wcaUserId": 298179,
      "wcaId": "2022QUIN17",
      "registrantId": 4,
      "countryIso2": "CO",
      "gender": "m",
      "registration": {
        "wcaRegistrationId": 1185043,
        "eventIds": [
          "222",
          "333",
          "333oh",
          "444",
          "clock",
          "pyram",
          "skewb"
        ],
        "status": "accepted",
        "isCompeting": true
      },
      "avatar": {
        "url": "https://avatars.worldcubeassociation.org/uploads/user/avatar/2022QUIN17/1728531501.jpg",
        "thumbUrl": "https://avatars.worldcubeassociation.org/uploads/user/avatar/2022QUIN17/1728531501_thumb.jpg"
      },
      "roles": [
        "organizer"
      ],
      "assignments": [],
      "personalBests": [
        {
          "eventId": "222",
          "best": 304,
          "worldRanking": 4038,
          "continentalRanking": 260,
          "nationalRanking": 53,
          "type": "average"
        },
        {
          "eventId": "333",
          "best": 1481,
          "worldRanking": 36346,
          "continentalRanking": 2751,
          "nationalRanking": 499,
          "type": "average"
        },
        {
          "eventId": "333oh",
          "best": 3108,
          "worldRanking": 22631,
          "continentalRanking": 1811,
          "nationalRanking": 309,
          "type": "average"
        },
        {
          "eventId": "444",
          "best": 9691,
          "worldRanking": 40458,
          "continentalRanking": 3263,
          "nationalRanking": 722,
          "type": "average"
        },
        {
          "eventId": "clock",
          "best": 2035,
          "worldRanking": 13672,
          "continentalRanking": 778,
          "nationalRanking": 188,
          "type": "average"
        },
        {
          "eventId": "pyram",
          "best": 774,
          "worldRanking": 14156,
          "continentalRanking": 976,
          "nationalRanking": 215,
          "type": "average"
        },
        {
          "eventId": "skewb",
          "best": 1041,
          "worldRanking": 20493,
          "continentalRanking": 1316,
          "nationalRanking": 321,
          "type": "average"
        },
        {
          "eventId": "222",
          "best": 173,
          "worldRanking": 5030,
          "continentalRanking": 365,
          "nationalRanking": 91,
          "type": "single"
        },
        {
          "eventId": "333",
          "best": 1235,
          "worldRanking": 37139,
          "continentalRanking": 2867,
          "nationalRanking": 531,
          "type": "single"
        },
        {
          "eventId": "333fm",
          "best": 62,
          "worldRanking": 10694,
          "continentalRanking": 755,
          "nationalRanking": 134,
          "type": "single"
        },
        {
          "eventId": "333oh",
          "best": 2800,
          "worldRanking": 27620,
          "continentalRanking": 2261,
          "nationalRanking": 411,
          "type": "single"
        },
        {
          "eventId": "444",
          "best": 6478,
          "worldRanking": 30928,
          "continentalRanking": 2431,
          "nationalRanking": 518,
          "type": "single"
        },
        {
          "eventId": "555",
          "best": 28350,
          "worldRanking": 35055,
          "continentalRanking": 2321,
          "nationalRanking": 442,
          "type": "single"
        },
        {
          "eventId": "clock",
          "best": 1738,
          "worldRanking": 14868,
          "continentalRanking": 842,
          "nationalRanking": 199,
          "type": "single"
        },
        {
          "eventId": "pyram",
          "best": 533,
          "worldRanking": 17319,
          "continentalRanking": 1242,
          "nationalRanking": 289,
          "type": "single"
        },
        {
          "eventId": "skewb",
          "best": 765,
          "worldRanking": 25163,
          "continentalRanking": 1586,
          "nationalRanking": 384,
          "type": "single"
        },
        {
          "eventId": "sq1",
          "best": 4390,
          "worldRanking": 15706,
          "continentalRanking": 1061,
          "nationalRanking": 200,
          "type": "single"
        }
      ],
      "extensions": []
    },
    {
      "name": "Santiago Ascue Quiroga",
      "wcaUserId": 391964,
      "wcaId": "2024QUIR01",
      "registrantId": 5,
      "countryIso2": "CO",
      "gender": "m",
      "registration": {
        "wcaRegistrationId": 1185217,
        "eventIds": [
          "222",
          "333",
          "333oh",
          "444",
          "pyram"
        ],
        "status": "accepted",
        "isCompeting": true
      },
      "avatar": null,
      "roles": [],
      "assignments": [],
      "personalBests": [
        {
          "eventId": "222",
          "best": 321,
          "worldRanking": 5089,
          "continentalRanking": 334,
          "nationalRanking": 75,
          "type": "average"
        },
        {
          "eventId": "333",
          "best": 1691,
          "worldRanking": 52082,
          "continentalRanking": 4146,
          "nationalRanking": 756,
          "type": "average"
        },
        {
          "eventId": "333oh",
          "best": 4684,
          "worldRanking": 39971,
          "continentalRanking": 3288,
          "nationalRanking": 623,
          "type": "average"
        },
        {
          "eventId": "444",
          "best": 7686,
          "worldRanking": 31861,
          "continentalRanking": 2519,
          "nationalRanking": 536,
          "type": "average"
        },
        {
          "eventId": "pyram",
          "best": 556,
          "worldRanking": 5504,
          "continentalRanking": 374,
          "nationalRanking": 93,
          "type": "average"
        },
        {
          "eventId": "222",
          "best": 230,
          "worldRanking": 11172,
          "continentalRanking": 844,
          "nationalRanking": 186,
          "type": "single"
        },
        {
          "eventId": "333",
          "best": 1290,
          "worldRanking": 42115,
          "continentalRanking": 3313,
          "nationalRanking": 622,
          "type": "single"
        },
        {
          "eventId": "333oh",
          "best": 3375,
          "worldRanking": 36273,
          "continentalRanking": 2994,
          "nationalRanking": 569,
          "type": "single"
        },
        {
          "eventId": "444",
          "best": 6676,
          "worldRanking": 32599,
          "continentalRanking": 2570,
          "nationalRanking": 553,
          "type": "single"
        },
        {
          "eventId": "pyram",
          "best": 327,
          "worldRanking": 5032,
          "continentalRanking": 343,
          "nationalRanking": 85,
          "type": "single"
        }
      ],
      "extensions": []
    },
    {
      "name": "Juan Jacobo Góngora",
      "wcaUserId": 470507,
      "wcaId": "2025GONG03",
      "registrantId": 6,
      "countryIso2": "CO",
      "gender": "m",
      "registration": {
        "wcaRegistrationId": 1185998,
        "eventIds": [
          "222",
          "333",
          "333oh",
          "444"
        ],
        "status": "accepted",
        "isCompeting": true
      },
      "avatar": null,
      "roles": [],
      "assignments": [],
      "personalBests": [
        {
          "eventId": "222",
          "best": 1046,
          "worldRanking": 105906,
          "continentalRanking": 8599,
          "nationalRanking": 1854,
          "type": "average"
        },
        {
          "eventId": "333",
          "best": 4505,
          "worldRanking": 186092,
          "continentalRanking": 17364,
          "nationalRanking": 3474,
          "type": "average"
        },
        {
          "eventId": "222",
          "best": 440,
          "worldRanking": 52498,
          "continentalRanking": 4169,
          "nationalRanking": 905,
          "type": "single"
        },
        {
          "eventId": "333",
          "best": 3666,
          "worldRanking": 185486,
          "continentalRanking": 17337,
          "nationalRanking": 3501,
          "type": "single"
        }
      ],
      "extensions": []
    },
    {
      "name": "Luis Carlos Gomez Velez",
      "wcaUserId": 253551,
      "wcaId": "2022VELE03",
      "registrantId": 7,
      "countryIso2": "CO",
      "gender": "m",
      "registration": {
        "wcaRegistrationId": 1186595,
        "eventIds": [
          "222",
          "333",
          "444"
        ],
        "status": "accepted",
        "isCompeting": true
      },
      "avatar": null,
      "roles": [],
      "assignments": [],
      "personalBests": [
        {
          "eventId": "222",
          "best": 786,
          "worldRanking": 76480,
          "continentalRanking": 5842,
          "nationalRanking": 1228,
          "type": "average"
        },
        {
          "eventId": "333",
          "best": 1553,
          "worldRanking": 41788,
          "continentalRanking": 3245,
          "nationalRanking": 583,
          "type": "average"
        },
        {
          "eventId": "444",
          "best": 5867,
          "worldRanking": 19217,
          "continentalRanking": 1475,
          "nationalRanking": 293,
          "type": "average"
        },
        {
          "eventId": "222",
          "best": 364,
          "worldRanking": 36097,
          "continentalRanking": 2825,
          "nationalRanking": 632,
          "type": "single"
        },
        {
          "eventId": "333",
          "best": 1189,
          "worldRanking": 33221,
          "continentalRanking": 2557,
          "nationalRanking": 468,
          "type": "single"
        },
        {
          "eventId": "444",
          "best": 5135,
          "worldRanking": 19282,
          "continentalRanking": 1482,
          "nationalRanking": 299,
          "type": "single"
        },
        {
          "eventId": "555",
          "best": 15350,
          "worldRanking": 24497,
          "continentalRanking": 1733,
          "nationalRanking": 360,
          "type": "single"
        }
      ],
      "extensions": []
    },
    {
      "name": "Nicolas Marin Urrea",
      "wcaUserId": 91359,
      "wcaId": "2018URRE01",
      "registrantId": 8,
      "countryIso2": "CO",
      "gender": "m",
      "registration": {
        "wcaRegistrationId": 1187144,
        "eventIds": [
          "222",
          "333",
          "333oh",
          "444",
          "clock",
          "pyram",
          "skewb"
        ],
        "status": "accepted",
        "isCompeting": true
      },
      "avatar": null,
      "roles": [],
      "assignments": [],
      "personalBests": [
        {
          "eventId": "222",
          "best": 519,
          "worldRanking": 30052,
          "continentalRanking": 2139,
          "nationalRanking": 432,
          "type": "average"
        },
        {
          "eventId": "333",
          "best": 1539,
          "worldRanking": 40754,
          "continentalRanking": 3150,
          "nationalRanking": 564,
          "type": "average"
        },
        {
          "eventId": "333oh",
          "best": 3477,
          "worldRanking": 27601,
          "continentalRanking": 2246,
          "nationalRanking": 404,
          "type": "average"
        },
        {
          "eventId": "444",
          "best": 5783,
          "worldRanking": 18519,
          "continentalRanking": 1417,
          "nationalRanking": 277,
          "type": "average"
        },
        {
          "eventId": "555",
          "best": 11099,
          "worldRanking": 12376,
          "continentalRanking": 838,
          "nationalRanking": 175,
          "type": "average"
        },
        {
          "eventId": "666",
          "best": 24177,
          "worldRanking": 8527,
          "continentalRanking": 562,
          "nationalRanking": 129,
          "type": "average"
        },
        {
          "eventId": "clock",
          "best": 2351,
          "worldRanking": 15455,
          "continentalRanking": 905,
          "nationalRanking": 222,
          "type": "average"
        },
        {
          "eventId": "minx",
          "best": 7992,
          "worldRanking": 4719,
          "continentalRanking": 458,
          "nationalRanking": 95,
          "type": "average"
        },
        {
          "eventId": "pyram",
          "best": 600,
          "worldRanking": 6891,
          "continentalRanking": 475,
          "nationalRanking": 118,
          "type": "average"
        },
        {
          "eventId": "skewb",
          "best": 940,
          "worldRanking": 16695,
          "continentalRanking": 1104,
          "nationalRanking": 268,
          "type": "average"
        },
        {
          "eventId": "sq1",
          "best": 3380,
          "worldRanking": 8614,
          "continentalRanking": 564,
          "nationalRanking": 102,
          "type": "average"
        },
        {
          "eventId": "222",
          "best": 371,
          "worldRanking": 37633,
          "continentalRanking": 2947,
          "nationalRanking": 656,
          "type": "single"
        },
        {
          "eventId": "333",
          "best": 1187,
          "worldRanking": 33042,
          "continentalRanking": 2538,
          "nationalRanking": 463,
          "type": "single"
        },
        {
          "eventId": "333fm",
          "best": 50,
          "worldRanking": 8799,
          "continentalRanking": 620,
          "nationalRanking": 111,
          "type": "single"
        },
        {
          "eventId": "333oh",
          "best": 1792,
          "worldRanking": 9528,
          "continentalRanking": 719,
          "nationalRanking": 105,
          "type": "single"
        },
        {
          "eventId": "444",
          "best": 5186,
          "worldRanking": 19789,
          "continentalRanking": 1533,
          "nationalRanking": 310,
          "type": "single"
        },
        {
          "eventId": "555",
          "best": 10451,
          "worldRanking": 13748,
          "continentalRanking": 940,
          "nationalRanking": 196,
          "type": "single"
        },
        {
          "eventId": "666",
          "best": 23423,
          "worldRanking": 9496,
          "continentalRanking": 627,
          "nationalRanking": 137,
          "type": "single"
        },
        {
          "eventId": "777",
          "best": 35195,
          "worldRanking": 7899,
          "continentalRanking": 514,
          "nationalRanking": 114,
          "type": "single"
        },
        {
          "eventId": "clock",
          "best": 1785,
          "worldRanking": 15270,
          "continentalRanking": 865,
          "nationalRanking": 207,
          "type": "single"
        },
        {
          "eventId": "minx",
          "best": 6715,
          "worldRanking": 4039,
          "continentalRanking": 398,
          "nationalRanking": 82,
          "type": "single"
        },
        {
          "eventId": "pyram",
          "best": 282,
          "worldRanking": 3348,
          "continentalRanking": 223,
          "nationalRanking": 54,
          "type": "single"
        },
        {
          "eventId": "skewb",
          "best": 512,
          "worldRanking": 12185,
          "continentalRanking": 820,
          "nationalRanking": 212,
          "type": "single"
        },
        {
          "eventId": "sq1",
          "best": 3051,
          "worldRanking": 11221,
          "continentalRanking": 735,
          "nationalRanking": 132,
          "type": "single"
        }
      ],
      "extensions": []
    },
    {
      "name": "Fabián Andrés Mina Sandoval",
      "wcaUserId": 395018,
      "wcaId": "2023SAND38",
      "registrantId": 10,
      "countryIso2": "CO",
      "gender": "m",
      "registration": {
        "wcaRegistrationId": 1187567,
        "eventIds": [
          "222",
          "333",
          "333oh",
          "444",
          "skewb"
        ],
        "status": "accepted",
        "isCompeting": true
      },
      "avatar": {
        "url": "https://avatars.worldcubeassociation.org/uploads/user/avatar/2023SAND38/1724027442.jpg",
        "thumbUrl": "https://avatars.worldcubeassociation.org/uploads/user/avatar/2023SAND38/1724027442_thumb.jpg"
      },
      "roles": [],
      "assignments": [],
      "personalBests": [
        {
          "eventId": "222",
          "best": 301,
          "worldRanking": 3886,
          "continentalRanking": 248,
          "nationalRanking": 52,
          "type": "average"
        },
        {
          "eventId": "333",
          "best": 863,
          "worldRanking": 2671,
          "continentalRanking": 117,
          "nationalRanking": 16,
          "type": "average"
        },
        {
          "eventId": "333oh",
          "best": 1698,
          "worldRanking": 3232,
          "continentalRanking": 217,
          "nationalRanking": 35,
          "type": "average"
        },
        {
          "eventId": "444",
          "best": 4202,
          "worldRanking": 5533,
          "continentalRanking": 388,
          "nationalRanking": 78,
          "type": "average"
        },
        {
          "eventId": "555",
          "best": 11871,
          "worldRanking": 14242,
          "continentalRanking": 974,
          "nationalRanking": 199,
          "type": "average"
        },
        {
          "eventId": "skewb",
          "best": 1549,
          "worldRanking": 37622,
          "continentalRanking": 2228,
          "nationalRanking": 544,
          "type": "average"
        },
        {
          "eventId": "222",
          "best": 177,
          "worldRanking": 5328,
          "continentalRanking": 384,
          "nationalRanking": 96,
          "type": "single"
        },
        {
          "eventId": "333",
          "best": 716,
          "worldRanking": 3487,
          "continentalRanking": 187,
          "nationalRanking": 32,
          "type": "single"
        },
        {
          "eventId": "333oh",
          "best": 1265,
          "worldRanking": 2365,
          "continentalRanking": 160,
          "nationalRanking": 25,
          "type": "single"
        },
        {
          "eventId": "444",
          "best": 3519,
          "worldRanking": 4653,
          "continentalRanking": 325,
          "nationalRanking": 63,
          "type": "single"
        },
        {
          "eventId": "555",
          "best": 10260,
          "worldRanking": 13189,
          "continentalRanking": 896,
          "nationalRanking": 187,
          "type": "single"
        },
        {
          "eventId": "skewb",
          "best": 850,
          "worldRanking": 29379,
          "continentalRanking": 1820,
          "nationalRanking": 455,
          "type": "single"
        }
      ],
      "extensions": []
    },
    {
      "name": "Mariana Giraldo Quintero",
      "wcaUserId": 420642,
      "wcaId": "2024QUIN14",
      "registrantId": 13,
      "countryIso2": "CO",
      "gender": "f",
      "registration": {
        "wcaRegistrationId": 1189403,
        "eventIds": [
          "222",
          "333",
          "pyram"
        ],
        "status": "accepted",
        "isCompeting": true
      },
      "avatar": {
        "url": "https://avatars.worldcubeassociation.org/xgh9algdc1ya5v2e0cbiq81cipv6",
        "thumbUrl": "https://avatars.worldcubeassociation.org/g39gsyhk00s2op29rxwdkhfu2apw"
      },
      "roles": [
        "organizer"
      ],
      "assignments": [],
      "personalBests": [
        {
          "eventId": "222",
          "best": 1374,
          "worldRanking": 126604,
          "continentalRanking": 10572,
          "nationalRanking": 2300,
          "type": "average"
        },
        {
          "eventId": "333",
          "best": 5569,
          "worldRanking": 209887,
          "continentalRanking": 20325,
          "nationalRanking": 4103,
          "type": "average"
        },
        {
          "eventId": "pyram",
          "best": 2116,
          "worldRanking": 94312,
          "continentalRanking": 7091,
          "nationalRanking": 1613,
          "type": "average"
        },
        {
          "eventId": "222",
          "best": 646,
          "worldRanking": 93040,
          "continentalRanking": 7450,
          "nationalRanking": 1633,
          "type": "single"
        },
        {
          "eventId": "333",
          "best": 3459,
          "worldRanking": 178028,
          "continentalRanking": 16443,
          "nationalRanking": 3333,
          "type": "single"
        },
        {
          "eventId": "pyram",
          "best": 1286,
          "worldRanking": 84085,
          "continentalRanking": 6324,
          "nationalRanking": 1434,
          "type": "single"
        }
      ],
      "extensions": []
    },
    {
      "name": "Juan Felipe Gómez López",
      "wcaUserId": 162085,
      "wcaId": "2021LOPE01",
      "registrantId": 14,
      "countryIso2": "CO",
      "gender": "m",
      "registration": {
        "wcaRegistrationId": 1189412,
        "eventIds": [
          "222",
          "333",
          "333oh",
          "444",
          "clock"
        ],
        "status": "accepted",
        "isCompeting": true
      },
      "avatar": {
        "url": "https://avatars.worldcubeassociation.org/uploads/user/avatar/2021LOPE01/1710887215.jpg",
        "thumbUrl": "https://avatars.worldcubeassociation.org/uploads/user/avatar/2021LOPE01/1710887215_thumb.jpg"
      },
      "roles": [
        "delegate",
        "organizer"
      ],
      "assignments": [],
      "personalBests": [
        {
          "eventId": "222",
          "best": 601,
          "worldRanking": 44986,
          "continentalRanking": 3288,
          "nationalRanking": 671,
          "type": "average"
        },
        {
          "eventId": "333",
          "best": 1411,
          "worldRanking": 31099,
          "continentalRanking": 2308,
          "nationalRanking": 430,
          "type": "average"
        },
        {
          "eventId": "333fm",
          "best": 3800,
          "worldRanking": 2037,
          "continentalRanking": 136,
          "nationalRanking": 30,
          "type": "average"
        },
        {
          "eventId": "333oh",
          "best": 4907,
          "worldRanking": 41497,
          "continentalRanking": 3430,
          "nationalRanking": 658,
          "type": "average"
        },
        {
          "eventId": "444",
          "best": 9273,
          "worldRanking": 39174,
          "continentalRanking": 3155,
          "nationalRanking": 699,
          "type": "average"
        },
        {
          "eventId": "clock",
          "best": 1133,
          "worldRanking": 5695,
          "continentalRanking": 313,
          "nationalRanking": 80,
          "type": "average"
        },
        {
          "eventId": "pyram",
          "best": 1226,
          "worldRanking": 45504,
          "continentalRanking": 3129,
          "nationalRanking": 713,
          "type": "average"
        },
        {
          "eventId": "skewb",
          "best": 1516,
          "worldRanking": 36667,
          "continentalRanking": 2178,
          "nationalRanking": 526,
          "type": "average"
        },
        {
          "eventId": "222",
          "best": 401,
          "worldRanking": 44022,
          "continentalRanking": 3472,
          "nationalRanking": 768,
          "type": "single"
        },
        {
          "eventId": "333",
          "best": 1022,
          "worldRanking": 19599,
          "continentalRanking": 1431,
          "nationalRanking": 267,
          "type": "single"
        },
        {
          "eventId": "333fm",
          "best": 32,
          "worldRanking": 2174,
          "continentalRanking": 141,
          "nationalRanking": 26,
          "type": "single"
        },
        {
          "eventId": "333oh",
          "best": 3639,
          "worldRanking": 39560,
          "continentalRanking": 3277,
          "nationalRanking": 627,
          "type": "single"
        },
        {
          "eventId": "444",
          "best": 7228,
          "worldRanking": 36711,
          "continentalRanking": 2912,
          "nationalRanking": 624,
          "type": "single"
        },
        {
          "eventId": "clock",
          "best": 913,
          "worldRanking": 5408,
          "continentalRanking": 302,
          "nationalRanking": 73,
          "type": "single"
        },
        {
          "eventId": "pyram",
          "best": 941,
          "worldRanking": 55969,
          "continentalRanking": 4127,
          "nationalRanking": 962,
          "type": "single"
        },
        {
          "eventId": "skewb",
          "best": 754,
          "worldRanking": 24592,
          "continentalRanking": 1557,
          "nationalRanking": 376,
          "type": "single"
        }
      ],
      "extensions": []
    },
    {
      "name": "Miguel Ángel Angulo Vanegas",
      "wcaUserId": 413398,
      "wcaId": "2024VANE03",
      "registrantId": 15,
      "countryIso2": "CO",
      "gender": "m",
      "registration": {
        "wcaRegistrationId": 1191378,
        "eventIds": [
          "222",
          "333",
          "pyram"
        ],
        "status": "accepted",
        "isCompeting": true
      },
      "avatar": null,
      "roles": [],
      "assignments": [],
      "personalBests": [
        {
          "eventId": "222",
          "best": 677,
          "worldRanking": 58874,
          "continentalRanking": 4347,
          "nationalRanking": 900,
          "type": "average"
        },
        {
          "eventId": "333",
          "best": 2049,
          "worldRanking": 77372,
          "continentalRanking": 6455,
          "nationalRanking": 1247,
          "type": "average"
        },
        {
          "eventId": "pyram",
          "best": 2089,
          "worldRanking": 93493,
          "continentalRanking": 7011,
          "nationalRanking": 1591,
          "type": "average"
        },
        {
          "eventId": "222",
          "best": 552,
          "worldRanking": 75941,
          "continentalRanking": 6027,
          "nationalRanking": 1293,
          "type": "single"
        },
        {
          "eventId": "333",
          "best": 1934,
          "worldRanking": 95880,
          "continentalRanking": 8209,
          "nationalRanking": 1583,
          "type": "single"
        },
        {
          "eventId": "pyram",
          "best": 1296,
          "worldRanking": 84702,
          "continentalRanking": 6374,
          "nationalRanking": 1443,
          "type": "single"
        }
      ],
      "extensions": []
    },
    {
      "name": "Juan Esteban Angulo Vanegas",
      "wcaUserId": 392709,
      "wcaId": "2023VANE10",
      "registrantId": 16,
      "countryIso2": "CO",
      "gender": "m",
      "registration": {
        "wcaRegistrationId": 1191380,
        "eventIds": [
          "222",
          "333",
          "333oh",
          "444",
          "pyram",
          "skewb"
        ],
        "status": "accepted",
        "isCompeting": true
      },
      "avatar": null,
      "roles": [],
      "assignments": [],
      "personalBests": [
        {
          "eventId": "222",
          "best": 461,
          "worldRanking": 20497,
          "continentalRanking": 1441,
          "nationalRanking": 287,
          "type": "average"
        },
        {
          "eventId": "333",
          "best": 1720,
          "worldRanking": 54309,
          "continentalRanking": 4345,
          "nationalRanking": 801,
          "type": "average"
        },
        {
          "eventId": "333oh",
          "best": 2860,
          "worldRanking": 19074,
          "continentalRanking": 1525,
          "nationalRanking": 259,
          "type": "average"
        },
        {
          "eventId": "444",
          "best": 7625,
          "worldRanking": 31544,
          "continentalRanking": 2491,
          "nationalRanking": 528,
          "type": "average"
        },
        {
          "eventId": "pyram",
          "best": 672,
          "worldRanking": 9515,
          "continentalRanking": 654,
          "nationalRanking": 149,
          "type": "average"
        },
        {
          "eventId": "skewb",
          "best": 817,
          "worldRanking": 12221,
          "continentalRanking": 803,
          "nationalRanking": 190,
          "type": "average"
        },
        {
          "eventId": "222",
          "best": 340,
          "worldRanking": 31167,
          "continentalRanking": 2438,
          "nationalRanking": 546,
          "type": "single"
        },
        {
          "eventId": "333",
          "best": 1347,
          "worldRanking": 47291,
          "continentalRanking": 3755,
          "nationalRanking": 712,
          "type": "single"
        },
        {
          "eventId": "333oh",
          "best": 2737,
          "worldRanking": 26498,
          "continentalRanking": 2169,
          "nationalRanking": 384,
          "type": "single"
        },
        {
          "eventId": "444",
          "best": 6716,
          "worldRanking": 32886,
          "continentalRanking": 2594,
          "nationalRanking": 559,
          "type": "single"
        },
        {
          "eventId": "pyram",
          "best": 531,
          "worldRanking": 17161,
          "continentalRanking": 1230,
          "nationalRanking": 286,
          "type": "single"
        },
        {
          "eventId": "skewb",
          "best": 636,
          "worldRanking": 18476,
          "continentalRanking": 1205,
          "nationalRanking": 292,
          "type": "single"
        }
      ],
      "extensions": []
    },
    {
      "name": "Nicolas Valero Moreno",
      "wcaUserId": 394760,
      "wcaId": "2023MORE50",
      "registrantId": 17,
      "countryIso2": "CO",
      "gender": "m",
      "registration": {
        "wcaRegistrationId": 1191644,
        "eventIds": [
          "222",
          "333",
          "333oh",
          "444",
          "clock",
          "pyram",
          "skewb"
        ],
        "status": "accepted",
        "isCompeting": true
      },
      "avatar": {
        "url": "https://avatars.worldcubeassociation.org/uploads/user/avatar/2023MORE50/1728355300.png",
        "thumbUrl": "https://avatars.worldcubeassociation.org/uploads/user/avatar/2023MORE50/1728355300_thumb.png"
      },
      "roles": [],
      "assignments": [],
      "personalBests": [
        {
          "eventId": "222",
          "best": 630,
          "worldRanking": 50313,
          "continentalRanking": 3699,
          "nationalRanking": 764,
          "type": "average"
        },
        {
          "eventId": "333",
          "best": 1903,
          "worldRanking": 67447,
          "continentalRanking": 5503,
          "nationalRanking": 1041,
          "type": "average"
        },
        {
          "eventId": "333oh",
          "best": 6729,
          "worldRanking": 48053,
          "continentalRanking": 4133,
          "nationalRanking": 794,
          "type": "average"
        },
        {
          "eventId": "444",
          "best": 10271,
          "worldRanking": 42011,
          "continentalRanking": 3424,
          "nationalRanking": 755,
          "type": "average"
        },
        {
          "eventId": "clock",
          "best": 1147,
          "worldRanking": 5856,
          "continentalRanking": 325,
          "nationalRanking": 83,
          "type": "average"
        },
        {
          "eventId": "minx",
          "best": 15525,
          "worldRanking": 14905,
          "continentalRanking": 1459,
          "nationalRanking": 312,
          "type": "average"
        },
        {
          "eventId": "pyram",
          "best": 1078,
          "worldRanking": 33944,
          "continentalRanking": 2339,
          "nationalRanking": 529,
          "type": "average"
        },
        {
          "eventId": "skewb",
          "best": 963,
          "worldRanking": 17561,
          "continentalRanking": 1157,
          "nationalRanking": 282,
          "type": "average"
        },
        {
          "eventId": "222",
          "best": 404,
          "worldRanking": 44676,
          "continentalRanking": 3524,
          "nationalRanking": 777,
          "type": "single"
        },
        {
          "eventId": "333",
          "best": 1625,
          "worldRanking": 71607,
          "continentalRanking": 5936,
          "nationalRanking": 1128,
          "type": "single"
        },
        {
          "eventId": "333oh",
          "best": 4670,
          "worldRanking": 48838,
          "continentalRanking": 4141,
          "nationalRanking": 799,
          "type": "single"
        },
        {
          "eventId": "444",
          "best": 9368,
          "worldRanking": 49963,
          "continentalRanking": 3933,
          "nationalRanking": 852,
          "type": "single"
        },
        {
          "eventId": "clock",
          "best": 1050,
          "worldRanking": 7225,
          "continentalRanking": 404,
          "nationalRanking": 97,
          "type": "single"
        },
        {
          "eventId": "minx",
          "best": 11916,
          "worldRanking": 13680,
          "continentalRanking": 1332,
          "nationalRanking": 278,
          "type": "single"
        },
        {
          "eventId": "pyram",
          "best": 768,
          "worldRanking": 38627,
          "continentalRanking": 2825,
          "nationalRanking": 658,
          "type": "single"
        },
        {
          "eventId": "skewb",
          "best": 491,
          "worldRanking": 11085,
          "continentalRanking": 744,
          "nationalRanking": 192,
          "type": "single"
        }
      ],
      "extensions": []
    },
    {
      "name": "Sergio Andrés Cuervo Buritica",
      "wcaUserId": 354893,
      "wcaId": "2024BURI01",
      "registrantId": 18,
      "countryIso2": "CO",
      "gender": "m",
      "registration": {
        "wcaRegistrationId": 1192240,
        "eventIds": [
          "222",
          "333",
          "333oh",
          "444"
        ],
        "status": "accepted",
        "isCompeting": true
      },
      "avatar": {
        "url": "https://avatars.worldcubeassociation.org/uploads/user/avatar/2024BURI01/1713749664.jpg",
        "thumbUrl": "https://avatars.worldcubeassociation.org/uploads/user/avatar/2024BURI01/1713749664_thumb.jpg"
      },
      "roles": [],
      "assignments": [],
      "personalBests": [
        {
          "eventId": "333",
          "best": 1942,
          "worldRanking": 70143,
          "continentalRanking": 5746,
          "nationalRanking": 1095,
          "type": "average"
        },
        {
          "eventId": "333oh",
          "best": 4291,
          "worldRanking": 36718,
          "continentalRanking": 3005,
          "nationalRanking": 571,
          "type": "average"
        },
        {
          "eventId": "333",
          "best": 1671,
          "worldRanking": 75365,
          "continentalRanking": 6314,
          "nationalRanking": 1213,
          "type": "single"
        },
        {
          "eventId": "333oh",
          "best": 3727,
          "worldRanking": 40579,
          "continentalRanking": 3374,
          "nationalRanking": 643,
          "type": "single"
        }
      ],
      "extensions": []
    },
    {
      "name": "Samuel Martinez Sanchez",
      "wcaUserId": 149439,
      "wcaId": "2019SANC20",
      "registrantId": 19,
      "countryIso2": "CO",
      "gender": "m",
      "registration": {
        "wcaRegistrationId": 1193723,
        "eventIds": [
          "222",
          "333",
          "333oh",
          "444",
          "clock",
          "pyram",
          "skewb"
        ],
        "status": "accepted",
        "isCompeting": true
      },
      "avatar": {
        "url": "https://avatars.worldcubeassociation.org/uploads/user/avatar/2019SANC20/1583641707.jpg",
        "thumbUrl": "https://avatars.worldcubeassociation.org/uploads/user/avatar/2019SANC20/1583641707_thumb.jpg"
      },
      "roles": [],
      "assignments": [],
      "personalBests": [
        {
          "eventId": "222",
          "best": 339,
          "worldRanking": 6357,
          "continentalRanking": 417,
          "nationalRanking": 91,
          "type": "average"
        },
        {
          "eventId": "333",
          "best": 953,
          "worldRanking": 5180,
          "continentalRanking": 296,
          "nationalRanking": 50,
          "type": "average"
        },
        {
          "eventId": "333bf",
          "best": 8456,
          "worldRanking": 1056,
          "continentalRanking": 61,
          "nationalRanking": 10,
          "type": "average"
        },
        {
          "eventId": "333fm",
          "best": 4300,
          "worldRanking": 3271,
          "continentalRanking": 219,
          "nationalRanking": 49,
          "type": "average"
        },
        {
          "eventId": "333oh",
          "best": 1879,
          "worldRanking": 5156,
          "continentalRanking": 386,
          "nationalRanking": 65,
          "type": "average"
        },
        {
          "eventId": "444",
          "best": 3400,
          "worldRanking": 1539,
          "continentalRanking": 85,
          "nationalRanking": 12,
          "type": "average"
        },
        {
          "eventId": "555",
          "best": 6732,
          "worldRanking": 1797,
          "continentalRanking": 99,
          "nationalRanking": 14,
          "type": "average"
        },
        {
          "eventId": "666",
          "best": 12425,
          "worldRanking": 1200,
          "continentalRanking": 68,
          "nationalRanking": 11,
          "type": "average"
        },
        {
          "eventId": "777",
          "best": 20267,
          "worldRanking": 1458,
          "continentalRanking": 87,
          "nationalRanking": 17,
          "type": "average"
        },
        {
          "eventId": "clock",
          "best": 789,
          "worldRanking": 2268,
          "continentalRanking": 121,
          "nationalRanking": 34,
          "type": "average"
        },
        {
          "eventId": "minx",
          "best": 5422,
          "worldRanking": 1154,
          "continentalRanking": 105,
          "nationalRanking": 15,
          "type": "average"
        },
        {
          "eventId": "pyram",
          "best": 566,
          "worldRanking": 5817,
          "continentalRanking": 393,
          "nationalRanking": 97,
          "type": "average"
        },
        {
          "eventId": "skewb",
          "best": 506,
          "worldRanking": 2829,
          "continentalRanking": 178,
          "nationalRanking": 42,
          "type": "average"
        },
        {
          "eventId": "sq1",
          "best": 2273,
          "worldRanking": 4392,
          "continentalRanking": 264,
          "nationalRanking": 47,
          "type": "average"
        },
        {
          "eventId": "222",
          "best": 141,
          "worldRanking": 2664,
          "continentalRanking": 152,
          "nationalRanking": 38,
          "type": "single"
        },
        {
          "eventId": "333",
          "best": 741,
          "worldRanking": 4229,
          "continentalRanking": 236,
          "nationalRanking": 43,
          "type": "single"
        },
        {
          "eventId": "333bf",
          "best": 6049,
          "worldRanking": 1336,
          "continentalRanking": 81,
          "nationalRanking": 10,
          "type": "single"
        },
        {
          "eventId": "333fm",
          "best": 35,
          "worldRanking": 3250,
          "continentalRanking": 216,
          "nationalRanking": 44,
          "type": "single"
        },
        {
          "eventId": "333mbf",
          "best": 950087200,
          "worldRanking": 1521,
          "continentalRanking": 99,
          "nationalRanking": 14,
          "type": "single"
        },
        {
          "eventId": "333oh",
          "best": 1293,
          "worldRanking": 2645,
          "continentalRanking": 186,
          "nationalRanking": 33,
          "type": "single"
        },
        {
          "eventId": "444",
          "best": 2694,
          "worldRanking": 828,
          "continentalRanking": 50,
          "nationalRanking": 7,
          "type": "single"
        },
        {
          "eventId": "444bf",
          "best": 30944,
          "worldRanking": 419,
          "continentalRanking": 20,
          "nationalRanking": 5,
          "type": "single"
        },
        {
          "eventId": "555",
          "best": 5957,
          "worldRanking": 1665,
          "continentalRanking": 85,
          "nationalRanking": 14,
          "type": "single"
        },
        {
          "eventId": "555bf",
          "best": 83800,
          "worldRanking": 352,
          "continentalRanking": 18,
          "nationalRanking": 5,
          "type": "single"
        },
        {
          "eventId": "666",
          "best": 11488,
          "worldRanking": 1165,
          "continentalRanking": 63,
          "nationalRanking": 12,
          "type": "single"
        },
        {
          "eventId": "777",
          "best": 19317,
          "worldRanking": 1541,
          "continentalRanking": 90,
          "nationalRanking": 20,
          "type": "single"
        },
        {
          "eventId": "clock",
          "best": 709,
          "worldRanking": 2914,
          "continentalRanking": 161,
          "nationalRanking": 43,
          "type": "single"
        },
        {
          "eventId": "minx",
          "best": 4359,
          "worldRanking": 705,
          "continentalRanking": 61,
          "nationalRanking": 9,
          "type": "single"
        },
        {
          "eventId": "pyram",
          "best": 276,
          "worldRanking": 3142,
          "continentalRanking": 207,
          "nationalRanking": 49,
          "type": "single"
        },
        {
          "eventId": "skewb",
          "best": 248,
          "worldRanking": 1640,
          "continentalRanking": 106,
          "nationalRanking": 26,
          "type": "single"
        },
        {
          "eventId": "sq1",
          "best": 1798,
          "worldRanking": 5129,
          "continentalRanking": 318,
          "nationalRanking": 62,
          "type": "single"
        }
      ],
      "extensions": []
    },
    {
      "name": "Gabriel Perafan Bonilla",
      "wcaUserId": 394419,
      "wcaId": "2023BONI05",
      "registrantId": 20,
      "countryIso2": "CO",
      "gender": "m",
      "registration": {
        "wcaRegistrationId": 1194256,
        "eventIds": [
          "222",
          "333",
          "333oh",
          "clock",
          "pyram"
        ],
        "status": "accepted",
        "isCompeting": true
      },
      "avatar": {
        "url": "https://avatars.worldcubeassociation.org/ctn9n31qhm1ln5qeozcps0kub6hd",
        "thumbUrl": "https://avatars.worldcubeassociation.org/d9bityso8ygojzhzpisinwhk1guu"
      },
      "roles": [],
      "assignments": [],
      "personalBests": [
        {
          "eventId": "222",
          "best": 414,
          "worldRanking": 13908,
          "continentalRanking": 966,
          "nationalRanking": 197,
          "type": "average"
        },
        {
          "eventId": "333",
          "best": 1243,
          "worldRanking": 19669,
          "continentalRanking": 1391,
          "nationalRanking": 242,
          "type": "average"
        },
        {
          "eventId": "333oh",
          "best": 2856,
          "worldRanking": 19014,
          "continentalRanking": 1520,
          "nationalRanking": 258,
          "type": "average"
        },
        {
          "eventId": "clock",
          "best": 1182,
          "worldRanking": 6231,
          "continentalRanking": 343,
          "nationalRanking": 87,
          "type": "average"
        },
        {
          "eventId": "pyram",
          "best": 865,
          "worldRanking": 19384,
          "continentalRanking": 1331,
          "nationalRanking": 288,
          "type": "average"
        },
        {
          "eventId": "222",
          "best": 301,
          "worldRanking": 23349,
          "continentalRanking": 1820,
          "nationalRanking": 390,
          "type": "single"
        },
        {
          "eventId": "333",
          "best": 1008,
          "worldRanking": 18534,
          "continentalRanking": 1341,
          "nationalRanking": 250,
          "type": "single"
        },
        {
          "eventId": "333oh",
          "best": 2346,
          "worldRanking": 19631,
          "continentalRanking": 1579,
          "nationalRanking": 269,
          "type": "single"
        },
        {
          "eventId": "clock",
          "best": 1093,
          "worldRanking": 7788,
          "continentalRanking": 436,
          "nationalRanking": 105,
          "type": "single"
        },
        {
          "eventId": "pyram",
          "best": 708,
          "worldRanking": 32776,
          "continentalRanking": 2383,
          "nationalRanking": 550,
          "type": "single"
        }
      ],
      "extensions": []
    },
    {
      "name": "Yosvaldo José Maizo",
      "wcaUserId": 381193,
      "wcaId": "2023MAIZ02",
      "registrantId": 21,
      "countryIso2": "VE",
      "gender": "m",
      "registration": {
        "wcaRegistrationId": 1194499,
        "eventIds": [
          "222",
          "333",
          "333oh",
          "444",
          "pyram"
        ],
        "status": "accepted",
        "isCompeting": true
      },
      "avatar": {
        "url": "https://avatars.worldcubeassociation.org/uploads/user/avatar/2023MAIZ02/1712714347.JPG",
        "thumbUrl": "https://avatars.worldcubeassociation.org/uploads/user/avatar/2023MAIZ02/1712714347_thumb.JPG"
      },
      "roles": [],
      "assignments": [],
      "personalBests": [
        {
          "eventId": "222",
          "best": 399,
          "worldRanking": 12091,
          "continentalRanking": 854,
          "nationalRanking": 34,
          "type": "average"
        },
        {
          "eventId": "333",
          "best": 1533,
          "worldRanking": 40280,
          "continentalRanking": 3099,
          "nationalRanking": 125,
          "type": "average"
        },
        {
          "eventId": "333fm",
          "best": 4933,
          "worldRanking": 4409,
          "continentalRanking": 304,
          "nationalRanking": 8,
          "type": "average"
        },
        {
          "eventId": "444",
          "best": 6829,
          "worldRanking": 26420,
          "continentalRanking": 2080,
          "nationalRanking": 82,
          "type": "average"
        },
        {
          "eventId": "pyram",
          "best": 962,
          "worldRanking": 25648,
          "continentalRanking": 1767,
          "nationalRanking": 78,
          "type": "average"
        },
        {
          "eventId": "222",
          "best": 262,
          "worldRanking": 16246,
          "continentalRanking": 1217,
          "nationalRanking": 45,
          "type": "single"
        },
        {
          "eventId": "333",
          "best": 1230,
          "worldRanking": 36689,
          "continentalRanking": 2840,
          "nationalRanking": 108,
          "type": "single"
        },
        {
          "eventId": "333fm",
          "best": 44,
          "worldRanking": 6843,
          "continentalRanking": 459,
          "nationalRanking": 20,
          "type": "single"
        },
        {
          "eventId": "444",
          "best": 6419,
          "worldRanking": 30427,
          "continentalRanking": 2388,
          "nationalRanking": 94,
          "type": "single"
        },
        {
          "eventId": "pyram",
          "best": 787,
          "worldRanking": 40510,
          "continentalRanking": 2962,
          "nationalRanking": 120,
          "type": "single"
        }
      ],
      "extensions": []
    },
    {
      "name": "Miguel Angel Erazo Romero",
      "wcaUserId": 477126,
      "wcaId": "2025ROME04",
      "registrantId": 22,
      "countryIso2": "CO",
      "gender": "m",
      "registration": {
        "wcaRegistrationId": 1195057,
        "eventIds": [
          "222",
          "333",
          "pyram",
          "skewb"
        ],
        "status": "accepted",
        "isCompeting": true
      },
      "avatar": null,
      "roles": [],
      "assignments": [],
      "personalBests": [
        {
          "eventId": "222",
          "best": 1410,
          "worldRanking": 128285,
          "continentalRanking": 10762,
          "nationalRanking": 2340,
          "type": "average"
        },
        {
          "eventId": "333",
          "best": 5070,
          "worldRanking": 200026,
          "continentalRanking": 19055,
          "nationalRanking": 3832,
          "type": "average"
        },
        {
          "eventId": "pyram",
          "best": 1546,
          "worldRanking": 68532,
          "continentalRanking": 4903,
          "nationalRanking": 1122,
          "type": "average"
        },
        {
          "eventId": "222",
          "best": 795,
          "worldRanking": 113374,
          "continentalRanking": 9334,
          "nationalRanking": 2041,
          "type": "single"
        },
        {
          "eventId": "333",
          "best": 4433,
          "worldRanking": 207917,
          "continentalRanking": 19967,
          "nationalRanking": 4035,
          "type": "single"
        },
        {
          "eventId": "pyram",
          "best": 1101,
          "worldRanking": 70490,
          "continentalRanking": 5216,
          "nationalRanking": 1190,
          "type": "single"
        }
      ],
      "extensions": []
    },
    {
      "name": "Emmanuel Castillo Alzate",
      "wcaUserId": 409745,
      "wcaId": "2024ALZA02",
      "registrantId": 23,
      "countryIso2": "CO",
      "gender": "m",
      "registration": {
        "wcaRegistrationId": 1195283,
        "eventIds": [
          "222",
          "333",
          "444",
          "pyram",
          "skewb"
        ],
        "status": "accepted",
        "isCompeting": true
      },
      "avatar": null,
      "roles": [],
      "assignments": [],
      "personalBests": [
        {
          "eventId": "222",
          "best": 486,
          "worldRanking": 24423,
          "continentalRanking": 1732,
          "nationalRanking": 346,
          "type": "average"
        },
        {
          "eventId": "333",
          "best": 1419,
          "worldRanking": 31692,
          "continentalRanking": 2351,
          "nationalRanking": 439,
          "type": "average"
        },
        {
          "eventId": "pyram",
          "best": 1188,
          "worldRanking": 42536,
          "continentalRanking": 2928,
          "nationalRanking": 673,
          "type": "average"
        },
        {
          "eventId": "skewb",
          "best": 2617,
          "worldRanking": 56205,
          "continentalRanking": 3175,
          "nationalRanking": 769,
          "type": "average"
        },
        {
          "eventId": "sq1",
          "best": 3308,
          "worldRanking": 8315,
          "continentalRanking": 543,
          "nationalRanking": 100,
          "type": "average"
        },
        {
          "eventId": "222",
          "best": 293,
          "worldRanking": 21840,
          "continentalRanking": 1673,
          "nationalRanking": 355,
          "type": "single"
        },
        {
          "eventId": "333",
          "best": 1282,
          "worldRanking": 41476,
          "continentalRanking": 3253,
          "nationalRanking": 614,
          "type": "single"
        },
        {
          "eventId": "pyram",
          "best": 796,
          "worldRanking": 41360,
          "continentalRanking": 3034,
          "nationalRanking": 706,
          "type": "single"
        },
        {
          "eventId": "skewb",
          "best": 1448,
          "worldRanking": 50392,
          "continentalRanking": 2942,
          "nationalRanking": 708,
          "type": "single"
        },
        {
          "eventId": "sq1",
          "best": 2476,
          "worldRanking": 8542,
          "continentalRanking": 558,
          "nationalRanking": 105,
          "type": "single"
        }
      ],
      "extensions": []
    },
    {
      "name": "Juan Manuel Porras Rojas",
      "wcaUserId": 411571,
      "wcaId": "2024ROJA05",
      "registrantId": 24,
      "countryIso2": "CO",
      "gender": "m",
      "registration": {
        "wcaRegistrationId": 1196278,
        "eventIds": [
          "222",
          "333",
          "333oh",
          "444",
          "skewb"
        ],
        "status": "accepted",
        "isCompeting": true
      },
      "avatar": {
        "url": "https://avatars.worldcubeassociation.org/9ktfe1h99p5r4z7r1h1czele2kmd",
        "thumbUrl": "https://avatars.worldcubeassociation.org/1eyvv5xhk3s4l83e5eoanxkdx012"
      },
      "roles": [],
      "assignments": [],
      "personalBests": [
        {
          "eventId": "222",
          "best": 621,
          "worldRanking": 48704,
          "continentalRanking": 3576,
          "nationalRanking": 734,
          "type": "average"
        },
        {
          "eventId": "333",
          "best": 1748,
          "worldRanking": 56472,
          "continentalRanking": 4526,
          "nationalRanking": 840,
          "type": "average"
        },
        {
          "eventId": "minx",
          "best": 11346,
          "worldRanking": 10463,
          "continentalRanking": 1032,
          "nationalRanking": 219,
          "type": "average"
        },
        {
          "eventId": "pyram",
          "best": 994,
          "worldRanking": 27915,
          "continentalRanking": 1907,
          "nationalRanking": 416,
          "type": "average"
        },
        {
          "eventId": "222",
          "best": 303,
          "worldRanking": 23744,
          "continentalRanking": 1858,
          "nationalRanking": 398,
          "type": "single"
        },
        {
          "eventId": "333",
          "best": 1493,
          "worldRanking": 60296,
          "continentalRanking": 4967,
          "nationalRanking": 948,
          "type": "single"
        },
        {
          "eventId": "minx",
          "best": 9102,
          "worldRanking": 8651,
          "continentalRanking": 862,
          "nationalRanking": 179,
          "type": "single"
        },
        {
          "eventId": "pyram",
          "best": 698,
          "worldRanking": 31843,
          "continentalRanking": 2312,
          "nationalRanking": 529,
          "type": "single"
        },
        {
          "eventId": "sq1",
          "best": 6741,
          "worldRanking": 19882,
          "continentalRanking": 1325,
          "nationalRanking": 252,
          "type": "single"
        }
      ],
      "extensions": []
    },
    {
      "name": "Nicolás Lasso Peña",
      "wcaUserId": 17111,
      "wcaId": "2013PENA05",
      "registrantId": null,
      "countryIso2": "CO",
      "gender": "m",
      "registration": null,
      "avatar": {
        "url": "https://avatars.worldcubeassociation.org/higl1mzz9movazpbo8ukf5xxezuo",
        "thumbUrl": "https://avatars.worldcubeassociation.org/auet2yya8098ziw3k32nx7zwvfod"
      },
      "roles": [
        "organizer"
      ],
      "assignments": [],
      "personalBests": [
        {
          "eventId": "222",
          "best": 290,
          "worldRanking": 3356,
          "continentalRanking": 197,
          "nationalRanking": 41,
          "type": "average"
        },
        {
          "eventId": "333",
          "best": 1001,
          "worldRanking": 6957,
          "continentalRanking": 424,
          "nationalRanking": 72,
          "type": "average"
        },
        {
          "eventId": "333bf",
          "best": 18455,
          "worldRanking": 2499,
          "continentalRanking": 163,
          "nationalRanking": 26,
          "type": "average"
        },
        {
          "eventId": "333fm",
          "best": 3733,
          "worldRanking": 1869,
          "continentalRanking": 123,
          "nationalRanking": 26,
          "type": "average"
        },
        {
          "eventId": "333ft",
          "best": 18640,
          "worldRanking": 1869,
          "continentalRanking": 156,
          "nationalRanking": 31,
          "type": "average"
        },
        {
          "eventId": "333oh",
          "best": 2188,
          "worldRanking": 8979,
          "continentalRanking": 666,
          "nationalRanking": 110,
          "type": "average"
        },
        {
          "eventId": "444",
          "best": 4145,
          "worldRanking": 5120,
          "continentalRanking": 346,
          "nationalRanking": 68,
          "type": "average"
        },
        {
          "eventId": "555",
          "best": 7048,
          "worldRanking": 2310,
          "continentalRanking": 130,
          "nationalRanking": 22,
          "type": "average"
        },
        {
          "eventId": "666",
          "best": 14314,
          "worldRanking": 2337,
          "continentalRanking": 137,
          "nationalRanking": 28,
          "type": "average"
        },
        {
          "eventId": "777",
          "best": 22730,
          "worldRanking": 2386,
          "continentalRanking": 136,
          "nationalRanking": 31,
          "type": "average"
        },
        {
          "eventId": "clock",
          "best": 2268,
          "worldRanking": 15050,
          "continentalRanking": 867,
          "nationalRanking": 209,
          "type": "average"
        },
        {
          "eventId": "minx",
          "best": 7777,
          "worldRanking": 4357,
          "continentalRanking": 422,
          "nationalRanking": 86,
          "type": "average"
        },
        {
          "eventId": "pyram",
          "best": 821,
          "worldRanking": 16774,
          "continentalRanking": 1168,
          "nationalRanking": 249,
          "type": "average"
        },
        {
          "eventId": "skewb",
          "best": 609,
          "worldRanking": 5432,
          "continentalRanking": 357,
          "nationalRanking": 87,
          "type": "average"
        },
        {
          "eventId": "sq1",
          "best": 4027,
          "worldRanking": 10873,
          "continentalRanking": 697,
          "nationalRanking": 132,
          "type": "average"
        },
        {
          "eventId": "222",
          "best": 119,
          "worldRanking": 1517,
          "continentalRanking": 72,
          "nationalRanking": 15,
          "type": "single"
        },
        {
          "eventId": "333",
          "best": 875,
          "worldRanking": 10165,
          "continentalRanking": 670,
          "nationalRanking": 128,
          "type": "single"
        },
        {
          "eventId": "333bf",
          "best": 12918,
          "worldRanking": 3864,
          "continentalRanking": 233,
          "nationalRanking": 34,
          "type": "single"
        },
        {
          "eventId": "333fm",
          "best": 28,
          "worldRanking": 1026,
          "continentalRanking": 58,
          "nationalRanking": 10,
          "type": "single"
        },
        {
          "eventId": "333ft",
          "best": 16949,
          "worldRanking": 2252,
          "continentalRanking": 183,
          "nationalRanking": 38,
          "type": "single"
        },
        {
          "eventId": "333mbf",
          "best": 970058600,
          "worldRanking": 2391,
          "continentalRanking": 161,
          "nationalRanking": 27,
          "type": "single"
        },
        {
          "eventId": "333oh",
          "best": 1930,
          "worldRanking": 11996,
          "continentalRanking": 929,
          "nationalRanking": 144,
          "type": "single"
        },
        {
          "eventId": "444",
          "best": 3629,
          "worldRanking": 5448,
          "continentalRanking": 391,
          "nationalRanking": 74,
          "type": "single"
        },
        {
          "eventId": "555",
          "best": 6282,
          "worldRanking": 2213,
          "continentalRanking": 127,
          "nationalRanking": 24,
          "type": "single"
        },
        {
          "eventId": "666",
          "best": 13783,
          "worldRanking": 2678,
          "continentalRanking": 155,
          "nationalRanking": 33,
          "type": "single"
        },
        {
          "eventId": "777",
          "best": 20369,
          "worldRanking": 1948,
          "continentalRanking": 119,
          "nationalRanking": 26,
          "type": "single"
        },
        {
          "eventId": "clock",
          "best": 2001,
          "worldRanking": 17011,
          "continentalRanking": 960,
          "nationalRanking": 232,
          "type": "single"
        },
        {
          "eventId": "minx",
          "best": 6639,
          "worldRanking": 3907,
          "continentalRanking": 381,
          "nationalRanking": 77,
          "type": "single"
        },
        {
          "eventId": "pyram",
          "best": 416,
          "worldRanking": 9507,
          "continentalRanking": 686,
          "nationalRanking": 172,
          "type": "single"
        },
        {
          "eventId": "skewb",
          "best": 433,
          "worldRanking": 8396,
          "continentalRanking": 578,
          "nationalRanking": 154,
          "type": "single"
        },
        {
          "eventId": "sq1",
          "best": 2758,
          "worldRanking": 9931,
          "continentalRanking": 649,
          "nationalRanking": 117,
          "type": "single"
        }
      ],
      "extensions": []
    }
  ],
  "events": [
    {
      "id": "333",
      "rounds": [
        {
          "id": "333-r1",
          "format": "a",
          "timeLimit": {
            "centiseconds": 30000,
            "cumulativeRoundIds": []
          },
          "cutoff": null,
          "advancementCondition": {
            "type": "percent",
            "level": 50
          },
          "scrambleSetCount": 1,
          "results": [],
          "extensions": []
        },
        {
          "id": "333-r2",
          "format": "a",
          "timeLimit": {
            "centiseconds": 30000,
            "cumulativeRoundIds": []
          },
          "cutoff": null,
          "advancementCondition": {
            "type": "ranking",
            "level": 8
          },
          "scrambleSetCount": 1,
          "results": [],
          "extensions": []
        },
        {
          "id": "333-r3",
          "format": "a",
          "timeLimit": {
            "centiseconds": 30000,
            "cumulativeRoundIds": []
          },
          "cutoff": null,
          "advancementCondition": null,
          "scrambleSetCount": 1,
          "results": [],
          "extensions": []
        }
      ],
      "extensions": [],
      "qualification": null
    },
    {
      "id": "222",
      "rounds": [
        {
          "id": "222-r1",
          "format": "a",
          "timeLimit": {
            "centiseconds": 6000,
            "cumulativeRoundIds": []
          },
          "cutoff": null,
          "advancementCondition": {
            "type": "ranking",
            "level": 12
          },
          "scrambleSetCount": 1,
          "results": [],
          "extensions": []
        },
        {
          "id": "222-r2",
          "format": "a",
          "timeLimit": {
            "centiseconds": 6000,
            "cumulativeRoundIds": []
          },
          "cutoff": null,
          "advancementCondition": null,
          "scrambleSetCount": 1,
          "results": [],
          "extensions": []
        }
      ],
      "extensions": [],
      "qualification": null
    },
    {
      "id": "444",
      "rounds": [
        {
          "id": "444-r1",
          "format": "a",
          "timeLimit": {
            "centiseconds": 11000,
            "cumulativeRoundIds": []
          },
          "cutoff": {
            "numberOfAttempts": 2,
            "attemptResult": 8000
          },
          "advancementCondition": null,
          "scrambleSetCount": 1,
          "results": [],
          "extensions": []
        }
      ],
      "extensions": [],
      "qualification": null
    },
    {
      "id": "333oh",
      "rounds": [
        {
          "id": "333oh-r1",
          "format": "a",
          "timeLimit": {
            "centiseconds": 9000,
            "cumulativeRoundIds": []
          },
          "cutoff": {
            "numberOfAttempts": 2,
            "attemptResult": 6000
          },
          "advancementCondition": null,
          "scrambleSetCount": 1,
          "results": [],
          "extensions": []
        }
      ],
      "extensions": [],
      "qualification": null
    },
    {
      "id": "clock",
      "rounds": [
        {
          "id": "clock-r1",
          "format": "a",
          "timeLimit": {
            "centiseconds": 12000,
            "cumulativeRoundIds": []
          },
          "cutoff": null,
          "advancementCondition": {
            "type": "ranking",
            "level": 12
          },
          "scrambleSetCount": 1,
          "results": [],
          "extensions": []
        },
        {
          "id": "clock-r2",
          "format": "a",
          "timeLimit": {
            "centiseconds": 12000,
            "cumulativeRoundIds": []
          },
          "cutoff": null,
          "advancementCondition": null,
          "scrambleSetCount": 1,
          "results": [],
          "extensions": []
        }
      ],
      "extensions": [],
      "qualification": null
    },
    {
      "id": "pyram",
      "rounds": [
        {
          "id": "pyram-r1",
          "format": "a",
          "timeLimit": {
            "centiseconds": 6000,
            "cumulativeRoundIds": []
          },
          "cutoff": {
            "numberOfAttempts": 2,
            "attemptResult": 4000
          },
          "advancementCondition": null,
          "scrambleSetCount": 1,
          "results": [],
          "extensions": []
        }
      ],
      "extensions": [],
      "qualification": null
    },
    {
      "id": "skewb",
      "rounds": [
        {
          "id": "skewb-r1",
          "format": "a",
          "timeLimit": {
            "centiseconds": 6000,
            "cumulativeRoundIds": []
          },
          "cutoff": {
            "numberOfAttempts": 2,
            "attemptResult": 4000
          },
          "advancementCondition": null,
          "scrambleSetCount": 1,
          "results": [],
          "extensions": []
        }
      ],
      "extensions": [],
      "qualification": null
    }
  ],
  "schedule": {
    "startDate": "2025-08-23",
    "numberOfDays": 1,
    "venues": [
      {
        "id": 1,
        "name": "Salón de eventos",
        "latitudeMicrodegrees": 3584629,
        "longitudeMicrodegrees": -76498485,
        "countryIso2": "CO",
        "timezone": "America/Bogota",
        "rooms": [
          {
            "id": 1,
            "name": "Salón de eventos",
            "color": "#007c00",
            "activities": [
              {
                "id": 1,
                "name": "Montaje",
                "activityCode": "other-setup",
                "startTime": "2025-08-23T12:30:00Z",
                "endTime": "2025-08-23T13:00:00Z",
                "childActivities": [],
                "extensions": []
              },
              {
                "id": 2,
                "name": "Clock, Round 1",
                "activityCode": "clock-r1",
                "startTime": "2025-08-23T13:00:00Z",
                "endTime": "2025-08-23T13:40:00Z",
                "childActivities": [],
                "extensions": []
              },
              {
                "id": 3,
                "name": "4x4x4 Cube, Round 1",
                "activityCode": "444-r1",
                "startTime": "2025-08-23T13:40:00Z",
                "endTime": "2025-08-23T14:20:00Z",
                "childActivities": [],
                "extensions": []
              },
              {
                "id": 4,
                "name": "Skewb, Round 1",
                "activityCode": "skewb-r1",
                "startTime": "2025-08-23T14:20:00Z",
                "endTime": "2025-08-23T15:00:00Z",
                "childActivities": [],
                "extensions": []
              },
              {
                "id": 5,
                "name": "3x3x3 One-Handed, Round 1",
                "activityCode": "333oh-r1",
                "startTime": "2025-08-23T15:00:00Z",
                "endTime": "2025-08-23T15:40:00Z",
                "childActivities": [],
                "extensions": []
              },
              {
                "id": 6,
                "name": "Pyraminx, Round 1",
                "activityCode": "pyram-r1",
                "startTime": "2025-08-23T15:40:00Z",
                "endTime": "2025-08-23T16:20:00Z",
                "childActivities": [],
                "extensions": []
              },
              {
                "id": 7,
                "name": "2x2x2 Cube, Round 1",
                "activityCode": "222-r1",
                "startTime": "2025-08-23T16:20:00Z",
                "endTime": "2025-08-23T17:00:00Z",
                "childActivities": [],
                "extensions": []
              },
              {
                "id": 8,
                "name": "Almuerzo",
                "activityCode": "other-lunch",
                "startTime": "2025-08-23T17:00:00Z",
                "endTime": "2025-08-23T18:00:00Z",
                "childActivities": [],
                "extensions": []
              },
              {
                "id": 9,
                "name": "Tutorial",
                "activityCode": "other-tutorial",
                "startTime": "2025-08-23T18:00:00Z",
                "endTime": "2025-08-23T18:20:00Z",
                "childActivities": [],
                "extensions": []
              },
              {
                "id": 10,
                "name": "3x3x3 Cube, Round 1",
                "activityCode": "333-r1",
                "startTime": "2025-08-23T18:20:00Z",
                "endTime": "2025-08-23T19:40:00Z",
                "childActivities": [],
                "extensions": []
              },
              {
                "id": 11,
                "name": "Clock, Round 2",
                "activityCode": "clock-r2",
                "startTime": "2025-08-23T19:40:00Z",
                "endTime": "2025-08-23T20:10:00Z",
                "childActivities": [],
                "extensions": []
              },
              {
                "id": 12,
                "name": "3x3x3 Cube, Round 2",
                "activityCode": "333-r2",
                "startTime": "2025-08-23T20:10:00Z",
                "endTime": "2025-08-23T20:50:00Z",
                "childActivities": [],
                "extensions": []
              },
              {
                "id": 13,
                "name": "2x2x2 Cube, Round 2",
                "activityCode": "222-r2",
                "startTime": "2025-08-23T20:50:00Z",
                "endTime": "2025-08-23T21:20:00Z",
                "childActivities": [],
                "extensions": []
              },
              {
                "id": 14,
                "name": "3x3x3 Cube, Round 3",
                "activityCode": "333-r3",
                "startTime": "2025-08-23T21:20:00Z",
                "endTime": "2025-08-23T22:00:00Z",
                "childActivities": [],
                "extensions": []
              },
              {
                "id": 15,
                "name": "Premiación",
                "activityCode": "other-awards",
                "startTime": "2025-08-23T22:00:00Z",
                "endTime": "2025-08-23T22:30:00Z",
                "childActivities": [],
                "extensions": []
              }
            ],
            "extensions": []
          }
        ],
        "extensions": []
      }
    ]
  },
  "competitorLimit": 50,
  "extensions": [],
  "registrationInfo": {
    "openTime": "2025-07-20T00:00:00Z",
    "closeTime": "2025-08-20T00:00:00Z",
    "baseEntryFee": 2000000,
    "currencyCode": "COP",
    "onTheSpotRegistration": true,
    "useWcaRegistration": true
  }
}